Mashup_Py/102003146.py
Mashup_Anureet_102003146-0.0.3.dist-info/LICENSE
Mashup_Anureet_102003146-0.0.3.dist-info/METADATA
Mashup_Anureet_102003146-0.0.3.dist-info/WHEEL
Mashup_Anureet_102003146-0.0.3.dist-info/top_level.txt
Mashup_Anureet_102003146-0.0.3.dist-info/RECORD
