Metadata-Version: 2.1
Name: Mashup-Anureet-102003146
Version: 0.0.3
Summary: Mashup in Python.
Author: Anureet Kaur
Author-email: akaur7_be20@thapar.edu
License: MIT
Classifier: License :: OSI Approved :: MIT License
Classifier: Programming Language :: Python :: 3
Classifier: Programming Language :: Python :: 3.7
License-File: LICENSE
Requires-Dist: pytube
Requires-Dist: pydub
